<?xml version="1.0" encoding="UTF-8" ?>
<!DOCTYPE mapper PUBLIC "-//mybatis.org//DTD Mapper 3.0//EN" "http://mybatis.org/dtd/mybatis-3-mapper.dtd" >
<mapper namespace="com.dimon.xcrm.dao.XdicMapper" >
  <resultMap id="BaseResultMap" type="com.dimon.xcrm.pojo.Xdic" >
    <!--
      WARNING - @mbggenerated
      This element is automatically generated by MyBatis Generator, do not modify.
    -->
    <id column="XDIC_ID" property="xdicId" jdbcType="DECIMAL" />
    <result column="XDIC_TAB" property="xdicTab" jdbcType="VARCHAR" />
    <result column="XDIC_COL" property="xdicCol" jdbcType="VARCHAR" />
    <result column="XDIC_KEY" property="xdicKey" jdbcType="CHAR" />
    <result column="XDIC_VAL" property="xdicVal" jdbcType="VARCHAR" />
  </resultMap>
  <sql id="Base_Column_List" >
    <!--
      WARNING - @mbggenerated
      This element is automatically generated by MyBatis Generator, do not modify.
    -->
    XDIC_ID, XDIC_TAB, XDIC_COL, XDIC_KEY, XDIC_VAL
  </sql>
  <select id="selectByPrimaryKey" resultMap="BaseResultMap" parameterType="java.lang.Long" >
    <!--
      WARNING - @mbggenerated
      This element is automatically generated by MyBatis Generator, do not modify.
    -->
    select 
    <include refid="Base_Column_List" />
    from XDIC
    where XDIC_ID = #{xdicId,jdbcType=DECIMAL}
  </select>
  <delete id="deleteByPrimaryKey" parameterType="java.lang.Long" >
    <!--
      WARNING - @mbggenerated
      This element is automatically generated by MyBatis Generator, do not modify.
    -->
    delete from XDIC
    where XDIC_ID = #{xdicId,jdbcType=DECIMAL}
  </delete>
  <insert id="insert" parameterType="com.dimon.xcrm.pojo.Xdic" >
    <!--
      WARNING - @mbggenerated
      This element is automatically generated by MyBatis Generator, do not modify.
    -->
    insert into XDIC (XDIC_ID, XDIC_TAB, XDIC_COL, 
      XDIC_KEY, XDIC_VAL)
    values (#{xdicId,jdbcType=DECIMAL}, #{xdicTab,jdbcType=VARCHAR}, #{xdicCol,jdbcType=VARCHAR}, 
      #{xdicKey,jdbcType=CHAR}, #{xdicVal,jdbcType=VARCHAR})
  </insert>
  <insert id="insertSelective" parameterType="com.dimon.xcrm.pojo.Xdic" >
    <!--
      WARNING - @mbggenerated
      This element is automatically generated by MyBatis Generator, do not modify.
    -->
    insert into XDIC
    <trim prefix="(" suffix=")" suffixOverrides="," >
      <if test="xdicId != null" >
        XDIC_ID,
      </if>
      <if test="xdicTab != null" >
        XDIC_TAB,
      </if>
      <if test="xdicCol != null" >
        XDIC_COL,
      </if>
      <if test="xdicKey != null" >
        XDIC_KEY,
      </if>
      <if test="xdicVal != null" >
        XDIC_VAL,
      </if>
    </trim>
    <trim prefix="values (" suffix=")" suffixOverrides="," >
      <if test="xdicId != null" >
        #{xdicId,jdbcType=DECIMAL},
      </if>
      <if test="xdicTab != null" >
        #{xdicTab,jdbcType=VARCHAR},
      </if>
      <if test="xdicCol != null" >
        #{xdicCol,jdbcType=VARCHAR},
      </if>
      <if test="xdicKey != null" >
        #{xdicKey,jdbcType=CHAR},
      </if>
      <if test="xdicVal != null" >
        #{xdicVal,jdbcType=VARCHAR},
      </if>
    </trim>
  </insert>
  <update id="updateByPrimaryKeySelective" parameterType="com.dimon.xcrm.pojo.Xdic" >
    <!--
      WARNING - @mbggenerated
      This element is automatically generated by MyBatis Generator, do not modify.
    -->
    update XDIC
    <set >
      <if test="xdicTab != null" >
        XDIC_TAB = #{xdicTab,jdbcType=VARCHAR},
      </if>
      <if test="xdicCol != null" >
        XDIC_COL = #{xdicCol,jdbcType=VARCHAR},
      </if>
      <if test="xdicKey != null" >
        XDIC_KEY = #{xdicKey,jdbcType=CHAR},
      </if>
      <if test="xdicVal != null" >
        XDIC_VAL = #{xdicVal,jdbcType=VARCHAR},
      </if>
    </set>
    where XDIC_ID = #{xdicId,jdbcType=DECIMAL}
  </update>
  <update id="updateByPrimaryKey" parameterType="com.dimon.xcrm.pojo.Xdic" >
    <!--
      WARNING - @mbggenerated
      This element is automatically generated by MyBatis Generator, do not modify.
    -->
    update XDIC
    set XDIC_TAB = #{xdicTab,jdbcType=VARCHAR},
      XDIC_COL = #{xdicCol,jdbcType=VARCHAR},
      XDIC_KEY = #{xdicKey,jdbcType=CHAR},
      XDIC_VAL = #{xdicVal,jdbcType=VARCHAR}
    where XDIC_ID = #{xdicId,jdbcType=DECIMAL}
  </update>
</mapper>